statusboard_notify/__init__.py
statusboard_notify/admin.py
statusboard_notify/apps.py
statusboard_notify/models.py
statusboard_notify/utils.py
statusboard_notify/views.py
statusboard_notify/locale/it/LC_MESSAGES/django.mo
statusboard_notify/locale/it/LC_MESSAGES/django.po
statusboard_notify/management/__init__.py
statusboard_notify/management/commands/__init__.py
statusboard_notify/management/commands/send_notifications.py
statusboard_notify/migrations/0001_initial.py
statusboard_notify/migrations/__init__.py
statusboard_notify/templates/statusboard_notify/email.html
django_statusboard_notify-0.7.0.dist-info/LICENSE
django_statusboard_notify-0.7.0.dist-info/METADATA
django_statusboard_notify-0.7.0.dist-info/WHEEL
django_statusboard_notify-0.7.0.dist-info/top_level.txt
django_statusboard_notify-0.7.0.dist-info/RECORD
