Metadata-Version: 2.1
Name: django-statusboard-notify
Version: 0.7.0
Summary: Utility for django-statusboard to notify status changes
Home-page: http://github.com/edigiacomo/django-statusboard-notify
Author: Emanuele Di Giacomo
Author-email: emanuele@digiacomo.cc
License: GPLv2+
Classifier: Development Status :: 4 - Beta
Classifier: Environment :: Web Environment
Classifier: License :: OSI Approved :: GNU General Public License v2 or later (GPLv2+)
Classifier: Framework :: Django
Classifier: Framework :: Django :: 3.2
Classifier: Framework :: Django :: 4.1
Classifier: Framework :: Django :: 4.2
Classifier: Operating System :: OS Independent
Classifier: Programming Language :: Python
Classifier: Programming Language :: Python :: 3
Classifier: Programming Language :: Python :: 3.6
Classifier: Programming Language :: Python :: 3.7
Classifier: Programming Language :: Python :: 3.8
Classifier: Programming Language :: Python :: 3.9
Classifier: Programming Language :: Python :: 3.10
Classifier: Programming Language :: Python :: 3.11
Classifier: Topic :: Internet :: WWW/HTTP
Classifier: Topic :: Internet :: WWW/HTTP :: Dynamic Content
Requires-Python: >=3.6
License-File: LICENSE
Requires-Dist: django >=2.2
Requires-Dist: django-statusboard
Requires-Dist: pypandoc
Provides-Extra: with_matrix
Requires-Dist: matrix-nio ; extra == 'with_matrix'
Provides-Extra: with_telegram
Requires-Dist: python-telegram-bot ; extra == 'with_telegram'
